Metadata-Version: 2.4
Name: hello-world-sangeda
Version: 0.1.0
Summary: 一个简单的Hello World包
Home-page: https://github.com/你的用户名/项目名
Author: 您的名字
Author-email: aaa <1821724720@qq.com>
Project-URL: Homepage, https://github.com/sangeda/hello-world
Classifier: Programming Language :: Python :: 3
Classifier: License :: OSI Approved :: MIT License
Classifier: Operating System :: OS Independent
Requires-Python: >=3.6
License-File: LICENSE
Dynamic: author
Dynamic: home-page
Dynamic: license-file
Dynamic: requires-python
